config/__init__.py
config/account.py
config/laputa_config.py
config/user_config.py
laputa_base/__init__.py
laputa_base/base/__init__.py
laputa_base/base/base_android.py
laputa_base/config/__init__.py
laputa_base/config/account.py
laputa_base/config/laputa_config.py
laputa_base/config/user_config.py
laputa_base/test_run/__init__.py
laputa_base/util/__init__.py
laputa_base/util/android/__init__.py
laputa_base/util/android/cmd.py
laputa_base/util/android/drivers.py
laputa_base/util/android/get_case1.py
laputa_base/util/android/get_run_case_id1.py
laputa_base/util/android/init_phone.py
laputa_base/util/android/operation_excel.py
laputa_base/util/android/operation_json.py
laputa_base/util/android/server.py
laputa_base/util/android/test_run1.py
laputa_base/util/android/upload1.py
laputa_base/util/android/write_check.py
laputa_base-1.0.2.dist-info/LICENSE
laputa_base-1.0.2.dist-info/METADATA
laputa_base-1.0.2.dist-info/WHEEL
laputa_base-1.0.2.dist-info/top_level.txt
laputa_base-1.0.2.dist-info/RECORD
