Metadata-Version: 2.1
Name: laputa-base
Version: 1.0.2
Summary: laputa base frame
Home-page: https://git.nevint.com/zhiyang.liu.o/laputa_base.git
Author: zhiyang.liu
Author-email: zhiyang.liu.o@nio.com
License: MIT
Platform: UNKNOWN
Classifier: Programming Language :: Python :: 3
Classifier: License :: OSI Approved :: MIT License
Classifier: Operating System :: OS Independent
Requires-Dist: aircv (>=1.4.6)
Requires-Dist: allure-pytest (>=2.8.6)
Requires-Dist: Appium-Python-Client (>=0.34)
Requires-Dist: lxml (>=4.2.5)
Requires-Dist: matplotlib (>=3.0.2)
Requires-Dist: paramiko (>=2.4.2)
Requires-Dist: Pillow (>=5.3.0)
Requires-Dist: pytest (>=5.2.1)
Requires-Dist: pytest-forked (>=1.0.2)
Requires-Dist: pytest-html (>=1.19.0)
Requires-Dist: pytest-metadata (>=1.7.0)
Requires-Dist: pytest-rerunfailures (>=7.0)
Requires-Dist: pytest-xdist (>=1.30.0)
Requires-Dist: PyYAML (>=5.1.2)
Requires-Dist: requests (>=2.20.1)
Requires-Dist: requests-toolbelt (>=0.9.1)
Requires-Dist: xlrd (>=1.1.0)
Requires-Dist: XlsxWriter (>=1.1.8)
Requires-Dist: xlutils (>=2.0.0)
Requires-Dist: xlwt (>=1.3.0)
